{
  "generated_at": "2025-11-27 13:45:50",
  "count": 40,
  "channels": [
    {
      "id": "crich2",
      "name": "Sky Sports Cricket",
      "logo": "https://abusaeeidx.github.io/Tv-Channel-Logo/CricHD/V2.0/sky_sports_cricket.png",
      "m3u8": "https://jan.player0003.com/hls/dadosky2.m3u8?md6=ao1glZFA0cCs5S9yMxZBKA&expires=1764234345&s=NTIuMTYxLjUxLjE1MQ==",
      "headers": {
        "Referer": "https://bhalocast.com/",
        "Origin": "https://bhalocast.com"
      }
    },
    {
      "id": "gtv",
      "name": "T Sports BD",
      "logo": "https://abusaeeidx.github.io/Tv-Channel-Logo/CricHD/V2.0/new/tsportsbd.png",
      "m3u8": "https://jan.player0003.com/hls/t_sportsbd.m3u8?md6=L1ZVc6ahCFgEutbN7wBttg&expires=1764234345&s=NTIuMTYxLjUxLjE1MQ==",
      "headers": {
        "Referer": "https://bhalocast.com/",
        "Origin": "https://bhalocast.com"
      }
    },
    {
      "id": "willow",
      "name": "Willow",
      "logo": "https://abusaeeidx.github.io/Tv-Channel-Logo/CricHD/V2.0/willow.png",
      "m3u8": "https://jan.player0003.com/hls/dadowillc.m3u8?md6=c9CQoVNs4_3hLxKDecaksQ&expires=1764234345&s=NTIuMTYxLjUxLjE1MQ==",
      "headers": {
        "Referer": "https://bhalocast.com/",
        "Origin": "https://bhalocast.com"
      }
    },
    {
      "id": "willowextra",
      "name": "Willow Xtra",
      "logo": "https://abusaeeidx.github.io/Tv-Channel-Logo/CricHD/V2.0/willowextra.png",
      "m3u8": "https://jan.player0003.com/hls/dadowillc2.m3u8?md6=6Ljpw7NxgWpVuOlgBpYe8A&expires=1764234345&s=NTIuMTYxLjUxLjE1MQ==",
      "headers": {
        "Referer": "https://bhalocast.com/",
        "Origin": "https://bhalocast.com"
      }
    },
    {
      "id": "starsp",
      "name": "Star Sports 1",
      "logo": "https://abusaeeidx.github.io/Tv-Channel-Logo/CricHD/V2.0/star_sports_1.png",
      "m3u8": "https://jan.player0003.com/hls/starl1in.m3u8?md6=TWCEIDLfkuAvk1YEYuRhAw&expires=1764234345&s=NTIuMTYxLjUxLjE1MQ==",
      "headers": {
        "Referer": "https://bhalocast.com/",
        "Origin": "https://bhalocast.com"
      }
    },
    {
      "id": "starsp3",
      "name": "Star Sports 1 Hindi",
      "logo": "https://abusaeeidx.github.io/Tv-Channel-Logo/CricHD/V2.0/star_sports_1_hindi.png",
      "m3u8": "https://jan.player0003.com/hls/starhindi.m3u8?md6=y-obYDrsVZ6BoIMGuEdy5w&expires=1764234345&s=NTIuMTYxLjUxLjE1MQ==",
      "headers": {
        "Referer": "https://bhalocast.com/",
        "Origin": "https://bhalocast.com"
      }
    },
    {
      "id": "starsp2",
      "name": "Star Sports 2",
      "logo": "https://abusaeeidx.github.io/Tv-Channel-Logo/CricHD/V2.0/new/Star_Sports_2.png",
      "m3u8": "https://jan.player0003.com/hls/star2en.m3u8?md6=pHjbz5EIUjO38qZgXyZ18w&expires=1764234345&s=NTIuMTYxLjUxLjE1MQ==",
      "headers": {
        "Referer": "https://bhalocast.com/",
        "Origin": "https://bhalocast.com"
      }
    },
    {
      "id": "starsp3",
      "name": "Star Sports 3",
      "logo": "https://abusaeeidx.github.io/Tv-Channel-Logo/CricHD/V2.0/new/star_sports3.jpg",
      "m3u8": "https://jan.player0003.com/hls/starhindi.m3u8?md6=y-obYDrsVZ6BoIMGuEdy5w&expires=1764234345&s=NTIuMTYxLjUxLjE1MQ==",
      "headers": {
        "Referer": "https://bhalocast.com/",
        "Origin": "https://bhalocast.com"
      }
    },
    {
      "id": "ptvsp",
      "name": "PTV Sports",
      "logo": "https://abusaeeidx.github.io/Tv-Channel-Logo/CricHD/V2.0/ptv_sports.png",
      "m3u8": "https://jan.player0003.com/hls/ptvsp.m3u8?md6=ZODl7F00E3oMN5ApmFlibA&expires=1764234346&s=NTIuMTYxLjUxLjE1MQ==",
      "headers": {
        "Referer": "https://bhalocast.com/",
        "Origin": "https://bhalocast.com"
      }
    },
    {
      "id": "asports",
      "name": "A Sports",
      "logo": "https://abusaeeidx.github.io/Tv-Channel-Logo/CricHD/V2.0/a_sports.png",
      "m3u8": "https://jan.player0003.com/hls/asportsd.m3u8?md6=COEy-KxT33lN2-4SpWQQ_g&expires=1764234346&s=NTIuMTYxLjUxLjE1MQ==",
      "headers": {
        "Referer": "https://bhalocast.com/",
        "Origin": "https://bhalocast.com"
      }
    },
    {
      "id": "tensp",
      "name": "Ten Cricket",
      "logo": "https://abusaeeidx.github.io/Tv-Channel-Logo/CricHD/V2.0/new/ten_cricket.png",
      "m3u8": "https://jan.player0003.com/hls/tensp.m3u8?md6=yQtB6PCavhK7Z-sM-tXjDQ&expires=1764234346&s=NTIuMTYxLjUxLjE1MQ==",
      "headers": {
        "Referer": "https://bhalocast.com/",
        "Origin": "https://bhalocast.com"
      }
    },
    {
      "id": "geosuper",
      "name": "Geo Super",
      "logo": "https://abusaeeidx.github.io/Tv-Channel-Logo/CricHD/V2.0/new/geo.jpg",
      "m3u8": "https://jan.player0003.com/hls/geosp.m3u8?md6=pqRApt5ZIv3yWn6Yx6xoYg&expires=1764234346&s=NTIuMTYxLjUxLjE1MQ==",
      "headers": {
        "Referer": "https://bhalocast.com/",
        "Origin": "https://bhalocast.com"
      }
    },
    {
      "id": "astrocric",
      "name": "Astro Cricket",
      "logo": "https://abusaeeidx.github.io/Tv-Channel-Logo/CricHD/V2.0/astro_cricket.png",
      "m3u8": "https://jan.player0003.com/hls/astrocric.m3u8?md6=rsL4snaI5aKZMpAIshYMAw&expires=1764234346&s=NTIuMTYxLjUxLjE1MQ==",
      "headers": {
        "Referer": "https://bhalocast.com/",
        "Origin": "https://bhalocast.com"
      }
    },
    {
      "id": "fox501",
      "name": "Fox Cricket",
      "logo": "https://abusaeeidx.github.io/Tv-Channel-Logo/CricHD/V2.0/fox501.png",
      "m3u8": "https://jan.player0003.com/hls/cf0sp1.m3u8?md6=9zhrBpEAfrhuSGOvmoijdg&expires=1764234346&s=NTIuMTYxLjUxLjE1MQ==",
      "headers": {
        "Referer": "https://bhalocast.com/",
        "Origin": "https://bhalocast.com"
      }
    },
    {
      "id": "skysp1",
      "name": "Sky Sports Main Event",
      "logo": "https://abusaeeidx.github.io/Tv-Channel-Logo/CricHD/V2.0/sky_sports_main_event.png",
      "m3u8": "https://jan.player0003.com/hls/dadosky1.m3u8?md6=9MwE9wDXkEZm394b_ARPww&expires=1764234346&s=NTIuMTYxLjUxLjE1MQ==",
      "headers": {
        "Referer": "https://bhalocast.com/",
        "Origin": "https://bhalocast.com"
      }
    },
    {
      "id": "skyfb",
      "name": "Sky Sports Football",
      "logo": "https://abusaeeidx.github.io/Tv-Channel-Logo/CricHD/V2.0/skysportsf.png",
      "m3u8": "https://jan.player0003.com/hls/dadoskyfob.m3u8?md6=b80ceisOPGR083oDurHOQQ&expires=1764234346&s=NTIuMTYxLjUxLjE1MQ==",
      "headers": {
        "Referer": "https://bhalocast.com/",
        "Origin": "https://bhalocast.com"
      }
    },
    {
      "id": "skyarena",
      "name": "Sky Sports Arena",
      "logo": "https://abusaeeidx.github.io/Tv-Channel-Logo/CricHD/V2.0/sky_sports_areana.png",
      "m3u8": "https://jan.player0003.com/hls/dadoskyare.m3u8?md6=NsZuQLMvAeFwVFRno4RAFg&expires=1764234347&s=NTIuMTYxLjUxLjE1MQ==",
      "headers": {
        "Referer": "https://bhalocast.com/",
        "Origin": "https://bhalocast.com"
      }
    },
    {
      "id": "skysp3",
      "name": "Sky Sports Action",
      "logo": "https://abusaeeidx.github.io/Tv-Channel-Logo/CricHD/V2.0/skysportaction.png",
      "m3u8": "https://jan.player0003.com/hls/dadosky3.m3u8?md6=_xhEE7UhrnzIhetYC1sHOQ&expires=1764234347&s=NTIuMTYxLjUxLjE1MQ==",
      "headers": {
        "Referer": "https://bhalocast.com/",
        "Origin": "https://bhalocast.com"
      }
    },
    {
      "id": "skysp4",
      "name": "Sky Sports Golf",
      "logo": "https://abusaeeidx.github.io/Tv-Channel-Logo/CricHD/V2.0/skysportdglof.png",
      "m3u8": "https://jan.player0003.com/hls/dadoskygo.m3u8?md6=MHhe1cZcRwbceubcschMpA&expires=1764234347&s=NTIuMTYxLjUxLjE1MQ==",
      "headers": {
        "Referer": "https://bhalocast.com/",
        "Origin": "https://bhalocast.com"
      }
    },
    {
      "id": "skysp5",
      "name": "Sky Sports Premier League",
      "logo": "https://abusaeeidx.github.io/Tv-Channel-Logo/CricHD/V2.0/skysportspr.png",
      "m3u8": "https://jan.player0003.com/hls/dadoskypormi.m3u8?md6=XIn6WuaSCGquinyfEVuCBA&expires=1764234347&s=NTIuMTYxLjUxLjE1MQ==",
      "headers": {
        "Referer": "https://bhalocast.com/",
        "Origin": "https://bhalocast.com"
      }
    },
    {
      "id": "skyspf1",
      "name": "Sky Sports F1",
      "logo": "https://abusaeeidx.github.io/Tv-Channel-Logo/CricHD/V2.0/sky_sportsl.png",
      "m3u8": "https://jan.player0003.com/hls/dadoskyf17.m3u8?md6=0jGxwC7sxLHOEoSh-C1ysw&expires=1764234347&s=NTIuMTYxLjUxLjE1MQ==",
      "headers": {
        "Referer": "https://bhalocast.com/",
        "Origin": "https://bhalocast.com"
      }
    },
    {
      "id": "skymix",
      "name": "Sky Sports Mix",
      "logo": "https://abusaeeidx.github.io/Tv-Channel-Logo/CricHD/V2.0/skysportmix.png",
      "m3u8": "https://jan.player0003.com/hls/dadoskymoxo.m3u8?md6=QuO9s0OvtV3BvNHmr_Lmvg&expires=1764234347&s=NTIuMTYxLjUxLjE1MQ==",
      "headers": {
        "Referer": "https://bhalocast.com/",
        "Origin": "https://bhalocast.com"
      }
    },
    {
      "id": "skyten",
      "name": "Sky Sports Tennis",
      "logo": "https://abusaeeidx.github.io/Tv-Channel-Logo/CricHD/V2.0/sky_Sports_tenis.png",
      "m3u8": "https://jan.player0003.com/hls/dadoskyten.m3u8?md6=JTn4g6yN4hS0b0BZ1QpPAA&expires=1764234347&s=NTIuMTYxLjUxLjE1MQ==",
      "headers": {
        "Referer": "https://bhalocast.com/",
        "Origin": "https://bhalocast.com"
      }
    },
    {
      "id": "osncric",
      "name": "SuperSport Cricket",
      "logo": "https://abusaeeidx.github.io/Tv-Channel-Logo/CricHD/V2.0/new/sli.jpg",
      "m3u8": "https://jan.player0003.com/hls/super2cric.m3u8?md6=EOsA0moszwwXQ4EeAqOqPA&expires=1764234348&s=NTIuMTYxLjUxLjE1MQ==",
      "headers": {
        "Referer": "https://bhalocast.com/",
        "Origin": "https://bhalocast.com"
      }
    },
    {
      "id": "supersp9",
      "name": "SuperSport Premier League",
      "logo": "https://abusaeeidx.github.io/Tv-Channel-Logo/CricHD/V2.0/ssp.png",
      "m3u8": "https://jan.player0003.com/hls/superprem.m3u8?md6=lO17u3ivLlthJmbWdC09cw&expires=1764234348&s=NTIuMTYxLjUxLjE1MQ==",
      "headers": {
        "Referer": "https://bhalocast.com/",
        "Origin": "https://bhalocast.com"
      }
    },
    {
      "id": "supersp10",
      "name": "SuperSport LaLiga",
      "logo": "https://abusaeeidx.github.io/Tv-Channel-Logo/CricHD/V2.0/new/superla.jpg",
      "m3u8": "https://jan.player0003.com/hls/superlaliga.m3u8?md6=5j5zouDFsLH8F1N7CRkgLQ&expires=1764234348&s=NTIuMTYxLjUxLjE1MQ==",
      "headers": {
        "Referer": "https://bhalocast.com/",
        "Origin": "https://bhalocast.com"
      }
    },
    {
      "id": "supersp8",
      "name": "SuperSport Football",
      "logo": "https://abusaeeidx.github.io/Tv-Channel-Logo/CricHD/V2.0/new/Supersf.jpg",
      "m3u8": "https://jan.player0003.com/hls/superspfb.m3u8?md6=O5j96EuVU8wqPPH9CNpjCA&expires=1764234348&s=NTIuMTYxLjUxLjE1MQ==",
      "headers": {
        "Referer": "https://bhalocast.com/",
        "Origin": "https://bhalocast.com"
      }
    },
    {
      "id": "supersp3",
      "name": "SuperSport Action",
      "logo": "https://abusaeeidx.github.io/Tv-Channel-Logo/CricHD/V2.0/new/Supersa.jpg",
      "m3u8": "https://jan.player0003.com/hls/superspaction.m3u8?md6=c1caJaGFdHTFN3cWpfyJVw&expires=1764234348&s=NTIuMTYxLjUxLjE1MQ==",
      "headers": {
        "Referer": "https://bhalocast.com/",
        "Origin": "https://bhalocast.com"
      }
    },
    {
      "id": "supersp6",
      "name": "SuperSport GrandStand",
      "logo": "https://abusaeeidx.github.io/Tv-Channel-Logo/CricHD/V2.0/new/Supersg.jpg",
      "m3u8": "https://jan.player0003.com/hls/supergs.m3u8?md6=qs9NDTmA7tnVKR9sDRf1Fg&expires=1764234348&s=NTIuMTYxLjUxLjE1MQ==",
      "headers": {
        "Referer": "https://bhalocast.com/",
        "Origin": "https://bhalocast.com"
      }
    },
    {
      "id": "btsp1",
      "name": "TNT Sports 1",
      "logo": "https://abusaeeidx.github.io/Tv-Channel-Logo/CricHD/V2.0/new/tnt1.png",
      "m3u8": "https://jan.player0003.com/hls/bbtsop1.m3u8?md6=Myr3Xbi7gw1QNfTSUTHB2w&expires=1764234349&s=NTIuMTYxLjUxLjE1MQ==",
      "headers": {
        "Referer": "https://bhalocast.com/",
        "Origin": "https://bhalocast.com"
      }
    },
    {
      "id": "btsp2",
      "name": "TNT Sports 2",
      "logo": "https://abusaeeidx.github.io/Tv-Channel-Logo/CricHD/V2.0/new/tnt2.png",
      "m3u8": "https://jan.player0003.com/hls/bbtsop2.m3u8?md6=BeU7nH5aRHpLguq4a9trdQ&expires=1764234349&s=NTIuMTYxLjUxLjE1MQ==",
      "headers": {
        "Referer": "https://bhalocast.com/",
        "Origin": "https://bhalocast.com"
      }
    },
    {
      "id": "btsp3",
      "name": "TNT Sports 3",
      "logo": "https://abusaeeidx.github.io/Tv-Channel-Logo/CricHD/V2.0/new/tnt3.png",
      "m3u8": "https://jan.player0003.com/hls/bbtsop3.m3u8?md6=8I2XNcs_FS70ZlWGzBXNRQ&expires=1764234349&s=NTIuMTYxLjUxLjE1MQ==",
      "headers": {
        "Referer": "https://bhalocast.com/",
        "Origin": "https://bhalocast.com"
      }
    },
    {
      "id": "btespn",
      "name": "TNT Sports 4",
      "logo": "https://abusaeeidx.github.io/Tv-Channel-Logo/CricHD/V2.0/new/tnt4.png",
      "m3u8": "https://jan.player0003.com/hls/bbtsop4.m3u8?md6=0S5SLJOQzvNNuZyQVraBBg&expires=1764234349&s=NTIuMTYxLjUxLjE1MQ==",
      "headers": {
        "Referer": "https://bhalocast.com/",
        "Origin": "https://bhalocast.com"
      }
    },
    {
      "id": "ten1",
      "name": "Sony Sports Ten 1",
      "logo": "https://abusaeeidx.github.io/Tv-Channel-Logo/CricHD/V2.0/new/sony1.jpg",
      "m3u8": "https://jan.player0003.com/hls/ten1udco.m3u8?md6=g4eK8v_LHYBZ2Zd6mTsXfA&expires=1764234349&s=NTIuMTYxLjUxLjE1MQ==",
      "headers": {
        "Referer": "https://bhalocast.com/",
        "Origin": "https://bhalocast.com"
      }
    },
    {
      "id": "criclife1",
      "name": "CricLife 1",
      "logo": "https://abusaeeidx.github.io/Tv-Channel-Logo/CricHD/V2.0/new/criclife.jpg",
      "m3u8": "https://jan.player0003.com/hls/criclife1.m3u8?md6=2qzx1GnZY8P2ziHHkjpbdg&expires=1764234349&s=NTIuMTYxLjUxLjE1MQ==",
      "headers": {
        "Referer": "https://bhalocast.com/",
        "Origin": "https://bhalocast.com"
      }
    },
    {
      "id": "criclife2",
      "name": "CricLife 2",
      "logo": "https://abusaeeidx.github.io/Tv-Channel-Logo/CricHD/V2.0/new/criclife.jpg",
      "m3u8": "https://jan.player0003.com/hls/criclife2.m3u8?md6=-B0okVP6fo8REeQ1LEyIWg&expires=1764234349&s=NTIuMTYxLjUxLjE1MQ==",
      "headers": {
        "Referer": "https://bhalocast.com/",
        "Origin": "https://bhalocast.com"
      }
    },
    {
      "id": "eurosp1",
      "name": "Eurosport 1",
      "logo": "https://abusaeeidx.github.io/Tv-Channel-Logo/CricHD/V2.0/new/Eurosport1.jpg",
      "m3u8": "https://jan.player0003.com/hls/eurosp1.m3u8?md6=BAbK-y_Na96BpZO0Pc0F5A&expires=1764234349&s=NTIuMTYxLjUxLjE1MQ==",
      "headers": {
        "Referer": "https://bhalocast.com/",
        "Origin": "https://bhalocast.com"
      }
    },
    {
      "id": "eurosp2",
      "name": "Eurosport 2",
      "logo": "https://abusaeeidx.github.io/Tv-Channel-Logo/CricHD/V2.0/new/Eurosport2.jpg",
      "m3u8": "https://jan.player0003.com/hls/eurosp2.m3u8?md6=HKb_131FLcKL01pSSeZjYA&expires=1764234350&s=NTIuMTYxLjUxLjE1MQ==",
      "headers": {
        "Referer": "https://bhalocast.com/",
        "Origin": "https://bhalocast.com"
      }
    },
    {
      "id": "viaplaysp1",
      "name": "Premier Sports 1",
      "logo": "https://abusaeeidx.github.io/Tv-Channel-Logo/CricHD/V2.0/new/Premiers1.jpg",
      "m3u8": "https://jan.player0003.com/hls/viaplaysp1.m3u8?md6=r75uRTH6iXZmGoa_1LRfiA&expires=1764234350&s=NTIuMTYxLjUxLjE1MQ==",
      "headers": {
        "Referer": "https://bhalocast.com/",
        "Origin": "https://bhalocast.com"
      }
    },
    {
      "id": "viaplaysp2",
      "name": "Premier Sports 2",
      "logo": "https://abusaeeidx.github.io/Tv-Channel-Logo/CricHD/V2.0/new/Premiers2.jpg",
      "m3u8": "https://jan.player0003.com/hls/viaplaysp2.m3u8?md6=0Ro0Usi82dys-dB85kiDEg&expires=1764234350&s=NTIuMTYxLjUxLjE1MQ==",
      "headers": {
        "Referer": "https://bhalocast.com/",
        "Origin": "https://bhalocast.com"
      }
    }
  ]
}